adafruit_pcd8544.py
adafruit_circuitpython_pcd8544-1.2.21.dist-info/licenses/LICENSE
adafruit_circuitpython_pcd8544-1.2.21.dist-info/METADATA
adafruit_circuitpython_pcd8544-1.2.21.dist-info/WHEEL
adafruit_circuitpython_pcd8544-1.2.21.dist-info/top_level.txt
adafruit_circuitpython_pcd8544-1.2.21.dist-info/RECORD
