Metadata-Version: 2.4
Name: adafruit-circuitpython-pcd8544
Version: 1.2.21
Summary: CircuitPython display control library for Nokia PCD8544 monochrome displays.
Author-email: Adafruit Industries <circuitpython@adafruit.com>
License: MIT
Project-URL: Homepage, https://github.com/adafruit/Adafruit_CircuitPython_PCD8544
Keywords: adafruit,display,nokia,pcd8544,monochrome,displays,hardware,micropython,circuitpython
Classifier: Intended Audience :: Developers
Classifier: Topic :: Software Development :: Libraries
Classifier: Topic :: Software Development :: Embedded Systems
Classifier: Topic :: System :: Hardware
Classifier: License :: OSI Approved :: MIT License
Classifier: Programming Language :: Python :: 3
License-File: LICENSE
Requires-Dist: Adafruit-Blinka
Requires-Dist: adafruit-circuitpython-busdevice
Requires-Dist: adafruit-circuitpython-framebuf
Provides-Extra: optional
Dynamic: license-file
